yapayzekainterface/__init__.py
yapayzekainterface/otomasyondb.py
yapayzekainterface/yapayzekacore.py
yapayzekainterface/modeller/svchash3.pkl
yapayzeka-0.0.22.dist-info/LICENSE.txt
yapayzeka-0.0.22.dist-info/METADATA
yapayzeka-0.0.22.dist-info/WHEEL
yapayzeka-0.0.22.dist-info/top_level.txt
yapayzeka-0.0.22.dist-info/RECORD
