Metadata-Version: 2.1
Name: yapayzeka
Version: 0.0.22
Summary: makine öğrenimi denemesi
Home-page: https://github.com/oguz687/yapayzeka
Author: oguzhan
Author-email: oguzhan_687@hotmail.com
License: MIT
Platform: UNKNOWN
Classifier: Programming Language :: Python :: 3
Classifier: License :: OSI Approved :: MIT License
Classifier: Operating System :: OS Independent
Requires-Dist: beautifulsoup4 (==4.7.1)
Requires-Dist: joblib (==0.13.2)
Requires-Dist: numpy (==1.15.1)
Requires-Dist: pandas (==0.24.0)
Requires-Dist: path.py (==11.5.0)
Requires-Dist: pathlib2 (==2.3.3)
Requires-Dist: pymongo (==3.7.2)
Requires-Dist: scikit-image (==0.14.0)
Requires-Dist: scikit-learn (==0.19.2)
Requires-Dist: scipy (==1.1.0)
Requires-Dist: snowballstemmer (==1.2.1)
Requires-Dist: TurkishStemmer (==1.3)
Requires-Dist: urllib3 (==1.24.1)
